{
  "as_of": "2026-06-02T22:44:45Z",
  "windows": {
    "24h": {
      "total": {
        "sell_susd": 38814,
        "buy_susd": 34435,
        "net_susd": -4379
      },
      "venues": [
        {
          "id": "curve_susde",
          "dex": "curve",
          "label": "Curve sUSD/sUSDe",
          "chain": "Ethereum",
          "sell_susd": 21978,
          "buy_susd": 10987,
          "attribution_source": "illustrative",
          "swap_count": null,
          "programmatic_susd": null,
          "organic_susd": null
        },
        {
          "id": "uni_susd_snx",
          "dex": "uniswap",
          "label": "Uniswap V3 sUSD/SNX",
          "chain": "Ethereum",
          "sell_susd": 11194,
          "buy_susd": 17181,
          "attribution_source": "measured",
          "swap_count": 35,
          "programmatic_susd": 0,
          "organic_susd": 17181
        },
        {
          "id": "velo_usdc_susd",
          "dex": "velodrome",
          "label": "Velodrome V2 USDC/sUSD",
          "chain": "Optimism",
          "sell_susd": 2109,
          "buy_susd": 1506,
          "attribution_source": "measured",
          "swap_count": 1302,
          "programmatic_susd": 0,
          "organic_susd": 1506
        },
        {
          "id": "uni_susd_weth",
          "dex": "uniswap",
          "label": "Uniswap V2 sUSD/WETH",
          "chain": "Ethereum",
          "sell_susd": 3504,
          "buy_susd": 4721,
          "attribution_source": "measured",
          "swap_count": 35,
          "programmatic_susd": 0,
          "organic_susd": 4721
        },
        {
          "id": "sushi_susd_weth",
          "dex": "sushiswap",
          "label": "Sushiswap sUSD/WETH",
          "chain": "Ethereum",
          "sell_susd": 29,
          "buy_susd": 40,
          "attribution_source": "measured",
          "swap_count": 4,
          "programmatic_susd": 0,
          "organic_susd": 40
        }
      ],
      "sell_counter_assets": {
        "SNX": 0.3733,
        "USDC": 0.0996,
        "WETH": 0.1307,
        "sUSDe": 0.3964
      },
      "buy_counter_assets": {
        "SNX": 0.5628,
        "USDC": 0.0693,
        "WETH": 0.1574,
        "sUSDe": 0.2106
      },
      "buy_split": {
        "programmatic_susd": 2637,
        "organic_susd": 31798,
        "programmatic_share": 0.0766
      }
    },
    "7d": {
      "total": {
        "sell_susd": 244464,
        "buy_susd": 243128,
        "net_susd": -1336
      },
      "venues": [
        {
          "id": "curve_susde",
          "dex": "curve",
          "label": "Curve sUSD/sUSDe",
          "chain": "Ethereum",
          "sell_susd": 131559,
          "buy_susd": 121839,
          "attribution_source": "measured",
          "swap_count": 368,
          "programmatic_susd": 0,
          "organic_susd": 121839
        },
        {
          "id": "uni_susd_snx",
          "dex": "uniswap",
          "label": "Uniswap V3 sUSD/SNX",
          "chain": "Ethereum",
          "sell_susd": 73866,
          "buy_susd": 86668,
          "attribution_source": "measured",
          "swap_count": 219,
          "programmatic_susd": 0,
          "organic_susd": 86668
        },
        {
          "id": "velo_usdc_susd",
          "dex": "velodrome",
          "label": "Velodrome V2 USDC/sUSD",
          "chain": "Optimism",
          "sell_susd": 17702,
          "buy_susd": 12445,
          "attribution_source": "measured",
          "swap_count": 5197,
          "programmatic_susd": 0,
          "organic_susd": 12445
        },
        {
          "id": "uni_susd_weth",
          "dex": "uniswap",
          "label": "Uniswap V2 sUSD/WETH",
          "chain": "Ethereum",
          "sell_susd": 21052,
          "buy_susd": 21883,
          "attribution_source": "measured",
          "swap_count": 205,
          "programmatic_susd": 0,
          "organic_susd": 21883
        },
        {
          "id": "sushi_susd_weth",
          "dex": "sushiswap",
          "label": "Sushiswap sUSD/WETH",
          "chain": "Ethereum",
          "sell_susd": 285,
          "buy_susd": 293,
          "attribution_source": "measured",
          "swap_count": 31,
          "programmatic_susd": 0,
          "organic_susd": 293
        }
      ],
      "sell_counter_assets": {
        "sUSDe": 0.5382,
        "SNX": 0.3022,
        "USDC": 0.0724,
        "WETH": 0.0873
      },
      "buy_counter_assets": {
        "sUSDe": 0.5011,
        "SNX": 0.3565,
        "USDC": 0.0512,
        "WETH": 0.0912
      },
      "buy_split": {
        "programmatic_susd": 0,
        "organic_susd": 243128,
        "programmatic_share": 0.0
      }
    }
  }
}
