{
  "as_of": "2026-05-13T17:16:18Z",
  "windows": {
    "24h": {
      "total": {
        "sell_susd": 350135,
        "buy_susd": 263670,
        "net_susd": -86465
      },
      "venues": [
        {
          "id": "curve_susde",
          "dex": "curve",
          "label": "Curve sUSD/sUSDe",
          "chain": "Ethereum",
          "sell_susd": 179428,
          "buy_susd": 89700,
          "attribution_source": "illustrative",
          "swap_count": null,
          "programmatic_susd": null,
          "organic_susd": null
        },
        {
          "id": "uni_susd_snx",
          "dex": "uniswap",
          "label": "Uniswap V3 sUSD/SNX",
          "chain": "Ethereum",
          "sell_susd": 90350,
          "buy_susd": 64545,
          "attribution_source": "illustrative",
          "swap_count": null,
          "programmatic_susd": null,
          "organic_susd": null
        },
        {
          "id": "velo_usdc_susd",
          "dex": "velodrome",
          "label": "Velodrome V2 USDC/sUSD",
          "chain": "Optimism",
          "sell_susd": 19264,
          "buy_susd": 35587,
          "attribution_source": "measured",
          "swap_count": 1232,
          "programmatic_susd": 0,
          "organic_susd": 35587
        },
        {
          "id": "uni_susd_weth",
          "dex": "uniswap",
          "label": "Uniswap V2 sUSD/WETH",
          "chain": "Ethereum",
          "sell_susd": 32839,
          "buy_susd": 39553,
          "attribution_source": "measured",
          "swap_count": 151,
          "programmatic_susd": 0,
          "organic_susd": 39553
        },
        {
          "id": "sushi_susd_weth",
          "dex": "sushiswap",
          "label": "Sushiswap sUSD/WETH",
          "chain": "Ethereum",
          "sell_susd": 28254,
          "buy_susd": 34285,
          "attribution_source": "measured",
          "swap_count": 134,
          "programmatic_susd": 0,
          "organic_susd": 34285
        }
      ],
      "sell_counter_assets": {
        "USDC": 0.1167,
        "WETH": 0.2284,
        "sUSDe": 0.5393,
        "SNX": 0.1156
      },
      "buy_counter_assets": {
        "USDC": 0.1818,
        "WETH": 0.3151,
        "sUSDe": 0.3861,
        "SNX": 0.117
      },
      "buy_split": {
        "programmatic_susd": 37019,
        "organic_susd": 226651,
        "programmatic_share": 0.1404
      }
    },
    "7d": {
      "total": {
        "sell_susd": 672858,
        "buy_susd": 628092,
        "net_susd": -44766
      },
      "venues": [
        {
          "id": "curve_susde",
          "dex": "curve",
          "label": "Curve sUSD/sUSDe",
          "chain": "Ethereum",
          "sell_susd": 274851,
          "buy_susd": 263914,
          "attribution_source": "measured",
          "swap_count": 490,
          "programmatic_susd": 0,
          "organic_susd": 263914
        },
        {
          "id": "uni_susd_snx",
          "dex": "uniswap",
          "label": "Uniswap V3 sUSD/SNX",
          "chain": "Ethereum",
          "sell_susd": 164212,
          "buy_susd": 141333,
          "attribution_source": "measured",
          "swap_count": 348,
          "programmatic_susd": 0,
          "organic_susd": 141333
        },
        {
          "id": "velo_usdc_susd",
          "dex": "velodrome",
          "label": "Velodrome V2 USDC/sUSD",
          "chain": "Optimism",
          "sell_susd": 89556,
          "buy_susd": 81380,
          "attribution_source": "measured",
          "swap_count": 5657,
          "programmatic_susd": 0,
          "organic_susd": 81380
        },
        {
          "id": "uni_susd_weth",
          "dex": "uniswap",
          "label": "Uniswap V2 sUSD/WETH",
          "chain": "Ethereum",
          "sell_susd": 78386,
          "buy_susd": 76919,
          "attribution_source": "measured",
          "swap_count": 389,
          "programmatic_susd": 0,
          "organic_susd": 76919
        },
        {
          "id": "sushi_susd_weth",
          "dex": "sushiswap",
          "label": "Sushiswap sUSD/WETH",
          "chain": "Ethereum",
          "sell_susd": 65853,
          "buy_susd": 64546,
          "attribution_source": "measured",
          "swap_count": 343,
          "programmatic_susd": 0,
          "organic_susd": 64546
        }
      ],
      "sell_counter_assets": {
        "sUSDe": 0.4085,
        "SNX": 0.2441,
        "USDC": 0.1331,
        "WETH": 0.2144
      },
      "buy_counter_assets": {
        "sUSDe": 0.4202,
        "SNX": 0.225,
        "USDC": 0.1296,
        "WETH": 0.2252
      },
      "buy_split": {
        "programmatic_susd": 0,
        "organic_susd": 628092,
        "programmatic_share": 0.0
      }
    }
  }
}
