{
  "as_of": "2026-05-28T13:01:54Z",
  "windows": {
    "24h": {
      "total": {
        "sell_susd": 82440,
        "buy_susd": 110887,
        "net_susd": 28447
      },
      "venues": [
        {
          "id": "curve_susde",
          "dex": "curve",
          "label": "Curve sUSD/sUSDe",
          "chain": "Ethereum",
          "sell_susd": 58486,
          "buy_susd": 63456,
          "attribution_source": "measured",
          "swap_count": 99,
          "programmatic_susd": 0,
          "organic_susd": 63456
        },
        {
          "id": "uni_susd_snx",
          "dex": "uniswap",
          "label": "Uniswap V3 sUSD/SNX",
          "chain": "Ethereum",
          "sell_susd": 7085,
          "buy_susd": 34741,
          "attribution_source": "measured",
          "swap_count": 57,
          "programmatic_susd": 0,
          "organic_susd": 34741
        },
        {
          "id": "velo_usdc_susd",
          "dex": "velodrome",
          "label": "Velodrome V2 USDC/sUSD",
          "chain": "Optimism",
          "sell_susd": 3615,
          "buy_susd": 5424,
          "attribution_source": "measured",
          "swap_count": 775,
          "programmatic_susd": 0,
          "organic_susd": 5424
        },
        {
          "id": "uni_susd_weth",
          "dex": "uniswap",
          "label": "Uniswap V2 sUSD/WETH",
          "chain": "Ethereum",
          "sell_susd": 13114,
          "buy_susd": 7061,
          "attribution_source": "illustrative",
          "swap_count": null,
          "programmatic_susd": null,
          "organic_susd": null
        },
        {
          "id": "sushi_susd_weth",
          "dex": "sushiswap",
          "label": "Sushiswap sUSD/WETH",
          "chain": "Ethereum",
          "sell_susd": 140,
          "buy_susd": 205,
          "attribution_source": "measured",
          "swap_count": 11,
          "programmatic_susd": 0,
          "organic_susd": 205
        }
      ],
      "sell_counter_assets": {
        "sUSDe": 0.8208,
        "SNX": 0.1098,
        "USDC": 0.0566,
        "WETH": 0.0128
      },
      "buy_counter_assets": {
        "sUSDe": 0.6143,
        "SNX": 0.326,
        "USDC": 0.054,
        "WETH": 0.0057
      },
      "buy_split": {
        "programmatic_susd": 1695,
        "organic_susd": 109192,
        "programmatic_share": 0.0153
      }
    },
    "7d": {
      "total": {
        "sell_susd": 319849,
        "buy_susd": 349446,
        "net_susd": 29597
      },
      "venues": [
        {
          "id": "curve_susde",
          "dex": "curve",
          "label": "Curve sUSD/sUSDe",
          "chain": "Ethereum",
          "sell_susd": 181538,
          "buy_susd": 185474,
          "attribution_source": "measured",
          "swap_count": 432,
          "programmatic_susd": 0,
          "organic_susd": 185474
        },
        {
          "id": "uni_susd_snx",
          "dex": "uniswap",
          "label": "Uniswap V3 sUSD/SNX",
          "chain": "Ethereum",
          "sell_susd": 60610,
          "buy_susd": 81013,
          "attribution_source": "measured",
          "swap_count": 225,
          "programmatic_susd": 0,
          "organic_susd": 81013
        },
        {
          "id": "velo_usdc_susd",
          "dex": "velodrome",
          "label": "Velodrome V2 USDC/sUSD",
          "chain": "Optimism",
          "sell_susd": 41150,
          "buy_susd": 43191,
          "attribution_source": "measured",
          "swap_count": 6245,
          "programmatic_susd": 0,
          "organic_susd": 43191
        },
        {
          "id": "uni_susd_weth",
          "dex": "uniswap",
          "label": "Uniswap V2 sUSD/WETH",
          "chain": "Ethereum",
          "sell_susd": 31509,
          "buy_susd": 34459,
          "attribution_source": "measured",
          "swap_count": 285,
          "programmatic_susd": 0,
          "organic_susd": 34459
        },
        {
          "id": "sushi_susd_weth",
          "dex": "sushiswap",
          "label": "Sushiswap sUSD/WETH",
          "chain": "Ethereum",
          "sell_susd": 5042,
          "buy_susd": 5309,
          "attribution_source": "measured",
          "swap_count": 123,
          "programmatic_susd": 0,
          "organic_susd": 5309
        }
      ],
      "sell_counter_assets": {
        "sUSDe": 0.5676,
        "SNX": 0.1895,
        "USDC": 0.1287,
        "WETH": 0.1143
      },
      "buy_counter_assets": {
        "sUSDe": 0.5308,
        "SNX": 0.2318,
        "USDC": 0.1236,
        "WETH": 0.1138
      },
      "buy_split": {
        "programmatic_susd": 0,
        "organic_susd": 349446,
        "programmatic_share": 0.0
      }
    }
  }
}
