{
  "as_of": "2026-06-10T04:16:14Z",
  "windows": {
    "24h": {
      "total": {
        "sell_susd": 5167,
        "buy_susd": 4206,
        "net_susd": -961
      },
      "venues": [
        {
          "id": "curve_susde",
          "dex": "curve",
          "label": "Curve sUSD/sUSDe",
          "chain": "Ethereum",
          "sell_susd": 3404,
          "buy_susd": 3169,
          "attribution_source": "measured",
          "swap_count": 42,
          "programmatic_susd": 0,
          "organic_susd": 3169
        },
        {
          "id": "uni_susd_snx",
          "dex": "uniswap",
          "label": "Uniswap V3 sUSD/SNX",
          "chain": "Ethereum",
          "sell_susd": 1140,
          "buy_susd": 0,
          "attribution_source": "measured",
          "swap_count": 5,
          "programmatic_susd": 0,
          "organic_susd": 0
        },
        {
          "id": "velo_usdc_susd",
          "dex": "velodrome",
          "label": "Velodrome V2 USDC/sUSD",
          "chain": "Optimism",
          "sell_susd": 355,
          "buy_susd": 201,
          "attribution_source": "measured",
          "swap_count": 648,
          "programmatic_susd": 0,
          "organic_susd": 201
        },
        {
          "id": "uni_susd_weth",
          "dex": "uniswap",
          "label": "Uniswap V2 sUSD/WETH",
          "chain": "Ethereum",
          "sell_susd": 268,
          "buy_susd": 817,
          "attribution_source": "measured",
          "swap_count": 20,
          "programmatic_susd": 0,
          "organic_susd": 817
        },
        {
          "id": "sushi_susd_weth",
          "dex": "sushiswap",
          "label": "Sushiswap sUSD/WETH",
          "chain": "Ethereum",
          "sell_susd": 0,
          "buy_susd": 19,
          "attribution_source": "measured",
          "swap_count": 4,
          "programmatic_susd": 0,
          "organic_susd": 19
        }
      ],
      "sell_counter_assets": {
        "sUSDe": 0.6588,
        "SNX": 0.2206,
        "USDC": 0.0687,
        "WETH": 0.0519
      },
      "buy_counter_assets": {
        "sUSDe": 0.7534,
        "SNX": 0.0,
        "USDC": 0.0478,
        "WETH": 0.1988
      },
      "buy_split": {
        "programmatic_susd": 0,
        "organic_susd": 4206,
        "programmatic_share": 0.0
      }
    },
    "7d": {
      "total": {
        "sell_susd": 197437,
        "buy_susd": 157735,
        "net_susd": -39702
      },
      "venues": [
        {
          "id": "curve_susde",
          "dex": "curve",
          "label": "Curve sUSD/sUSDe",
          "chain": "Ethereum",
          "sell_susd": 92683,
          "buy_susd": 77015,
          "attribution_source": "measured",
          "swap_count": 556,
          "programmatic_susd": 0,
          "organic_susd": 77015
        },
        {
          "id": "uni_susd_snx",
          "dex": "uniswap",
          "label": "Uniswap V3 sUSD/SNX",
          "chain": "Ethereum",
          "sell_susd": 43668,
          "buy_susd": 30630,
          "attribution_source": "measured",
          "swap_count": 177,
          "programmatic_susd": 0,
          "organic_susd": 30630
        },
        {
          "id": "velo_usdc_susd",
          "dex": "velodrome",
          "label": "Velodrome V2 USDC/sUSD",
          "chain": "Optimism",
          "sell_susd": 39730,
          "buy_susd": 30152,
          "attribution_source": "measured",
          "swap_count": 11729,
          "programmatic_susd": 0,
          "organic_susd": 30152
        },
        {
          "id": "uni_susd_weth",
          "dex": "uniswap",
          "label": "Uniswap V2 sUSD/WETH",
          "chain": "Ethereum",
          "sell_susd": 21211,
          "buy_susd": 19822,
          "attribution_source": "measured",
          "swap_count": 277,
          "programmatic_susd": 0,
          "organic_susd": 19822
        },
        {
          "id": "sushi_susd_weth",
          "dex": "sushiswap",
          "label": "Sushiswap sUSD/WETH",
          "chain": "Ethereum",
          "sell_susd": 145,
          "buy_susd": 116,
          "attribution_source": "measured",
          "swap_count": 29,
          "programmatic_susd": 0,
          "organic_susd": 116
        }
      ],
      "sell_counter_assets": {
        "sUSDe": 0.4694,
        "SNX": 0.2212,
        "USDC": 0.2012,
        "WETH": 0.1082
      },
      "buy_counter_assets": {
        "sUSDe": 0.4883,
        "SNX": 0.1942,
        "USDC": 0.1912,
        "WETH": 0.1264
      },
      "buy_split": {
        "programmatic_susd": 0,
        "organic_susd": 157735,
        "programmatic_share": 0.0
      }
    }
  }
}
