{
  "as_of": "2026-05-12T21:01:55Z",
  "windows": {
    "24h": {
      "total": {
        "sell_susd": 180525,
        "buy_susd": 162814,
        "net_susd": -17711
      },
      "venues": [
        {
          "id": "curve_susde",
          "dex": "curve",
          "label": "Curve sUSD/sUSDe",
          "chain": "Ethereum",
          "sell_susd": 95349,
          "buy_susd": 47668,
          "attribution_source": "illustrative",
          "swap_count": null,
          "programmatic_susd": null,
          "organic_susd": null
        },
        {
          "id": "uni_susd_snx",
          "dex": "uniswap",
          "label": "Uniswap V3 sUSD/SNX",
          "chain": "Ethereum",
          "sell_susd": 31130,
          "buy_susd": 53337,
          "attribution_source": "measured",
          "swap_count": 106,
          "programmatic_susd": 0,
          "organic_susd": 53337
        },
        {
          "id": "velo_usdc_susd",
          "dex": "velodrome",
          "label": "Velodrome V2 USDC/sUSD",
          "chain": "Optimism",
          "sell_susd": 13696,
          "buy_susd": 17341,
          "attribution_source": "measured",
          "swap_count": 1213,
          "programmatic_susd": 0,
          "organic_susd": 17341
        },
        {
          "id": "uni_susd_weth",
          "dex": "uniswap",
          "label": "Uniswap V2 sUSD/WETH",
          "chain": "Ethereum",
          "sell_susd": 22991,
          "buy_susd": 25207,
          "attribution_source": "measured",
          "swap_count": 114,
          "programmatic_susd": 0,
          "organic_susd": 25207
        },
        {
          "id": "sushi_susd_weth",
          "dex": "sushiswap",
          "label": "Sushiswap sUSD/WETH",
          "chain": "Ethereum",
          "sell_susd": 17359,
          "buy_susd": 19261,
          "attribution_source": "measured",
          "swap_count": 80,
          "programmatic_susd": 0,
          "organic_susd": 19261
        }
      ],
      "sell_counter_assets": {
        "SNX": 0.2517,
        "USDC": 0.1181,
        "WETH": 0.2605,
        "sUSDe": 0.3697
      },
      "buy_counter_assets": {
        "SNX": 0.3861,
        "USDC": 0.1299,
        "WETH": 0.2907,
        "sUSDe": 0.1932
      },
      "buy_split": {
        "programmatic_susd": 11440,
        "organic_susd": 151374,
        "programmatic_share": 0.0703
      }
    },
    "7d": {
      "total": {
        "sell_susd": 502223,
        "buy_susd": 414659,
        "net_susd": -87564
      },
      "venues": [
        {
          "id": "curve_susde",
          "dex": "curve",
          "label": "Curve sUSD/sUSDe",
          "chain": "Ethereum",
          "sell_susd": 192085,
          "buy_susd": 174423,
          "attribution_source": "measured",
          "swap_count": 419,
          "programmatic_susd": 0,
          "organic_susd": 174423
        },
        {
          "id": "uni_susd_snx",
          "dex": "uniswap",
          "label": "Uniswap V3 sUSD/SNX",
          "chain": "Ethereum",
          "sell_susd": 132548,
          "buy_susd": 83729,
          "attribution_source": "measured",
          "swap_count": 271,
          "programmatic_susd": 0,
          "organic_susd": 83729
        },
        {
          "id": "velo_usdc_susd",
          "dex": "velodrome",
          "label": "Velodrome V2 USDC/sUSD",
          "chain": "Optimism",
          "sell_susd": 71632,
          "buy_susd": 57189,
          "attribution_source": "measured",
          "swap_count": 5592,
          "programmatic_susd": 0,
          "organic_susd": 57189
        },
        {
          "id": "uni_susd_weth",
          "dex": "uniswap",
          "label": "Uniswap V2 sUSD/WETH",
          "chain": "Ethereum",
          "sell_susd": 59017,
          "buy_susd": 55518,
          "attribution_source": "measured",
          "swap_count": 320,
          "programmatic_susd": 0,
          "organic_susd": 55518
        },
        {
          "id": "sushi_susd_weth",
          "dex": "sushiswap",
          "label": "Sushiswap sUSD/WETH",
          "chain": "Ethereum",
          "sell_susd": 46941,
          "buy_susd": 43800,
          "attribution_source": "measured",
          "swap_count": 261,
          "programmatic_susd": 0,
          "organic_susd": 43800
        }
      ],
      "sell_counter_assets": {
        "sUSDe": 0.3825,
        "SNX": 0.2639,
        "USDC": 0.1426,
        "WETH": 0.211
      },
      "buy_counter_assets": {
        "sUSDe": 0.4206,
        "SNX": 0.2019,
        "USDC": 0.1379,
        "WETH": 0.2395
      },
      "buy_split": {
        "programmatic_susd": 0,
        "organic_susd": 414659,
        "programmatic_share": 0.0
      }
    }
  }
}
