{
  "as_of": "2026-06-08T09:02:06Z",
  "windows": {
    "24h": {
      "total": {
        "sell_susd": 18900,
        "buy_susd": 16586,
        "net_susd": -2314
      },
      "venues": [
        {
          "id": "curve_susde",
          "dex": "curve",
          "label": "Curve sUSD/sUSDe",
          "chain": "Ethereum",
          "sell_susd": 8533,
          "buy_susd": 8179,
          "attribution_source": "measured",
          "swap_count": 77,
          "programmatic_susd": 0,
          "organic_susd": 8179
        },
        {
          "id": "uni_susd_snx",
          "dex": "uniswap",
          "label": "Uniswap V3 sUSD/SNX",
          "chain": "Ethereum",
          "sell_susd": 2084,
          "buy_susd": 0,
          "attribution_source": "measured",
          "swap_count": 8,
          "programmatic_susd": 0,
          "organic_susd": 0
        },
        {
          "id": "velo_usdc_susd",
          "dex": "velodrome",
          "label": "Velodrome V2 USDC/sUSD",
          "chain": "Optimism",
          "sell_susd": 6725,
          "buy_susd": 7360,
          "attribution_source": "measured",
          "swap_count": 1843,
          "programmatic_susd": 0,
          "organic_susd": 7360
        },
        {
          "id": "uni_susd_weth",
          "dex": "uniswap",
          "label": "Uniswap V2 sUSD/WETH",
          "chain": "Ethereum",
          "sell_susd": 1538,
          "buy_susd": 1041,
          "attribution_source": "measured",
          "swap_count": 38,
          "programmatic_susd": 0,
          "organic_susd": 1041
        },
        {
          "id": "sushi_susd_weth",
          "dex": "sushiswap",
          "label": "Sushiswap sUSD/WETH",
          "chain": "Ethereum",
          "sell_susd": 20,
          "buy_susd": 6,
          "attribution_source": "measured",
          "swap_count": 4,
          "programmatic_susd": 0,
          "organic_susd": 6
        }
      ],
      "sell_counter_assets": {
        "sUSDe": 0.4515,
        "SNX": 0.1103,
        "USDC": 0.3558,
        "WETH": 0.0824
      },
      "buy_counter_assets": {
        "sUSDe": 0.4931,
        "SNX": 0.0,
        "USDC": 0.4437,
        "WETH": 0.0631
      },
      "buy_split": {
        "programmatic_susd": 0,
        "organic_susd": 16586,
        "programmatic_share": 0.0
      }
    },
    "7d": {
      "total": {
        "sell_susd": 216603,
        "buy_susd": 183000,
        "net_susd": -33603
      },
      "venues": [
        {
          "id": "curve_susde",
          "dex": "curve",
          "label": "Curve sUSD/sUSDe",
          "chain": "Ethereum",
          "sell_susd": 102827,
          "buy_susd": 85955,
          "attribution_source": "measured",
          "swap_count": 565,
          "programmatic_susd": 0,
          "organic_susd": 85955
        },
        {
          "id": "uni_susd_snx",
          "dex": "uniswap",
          "label": "Uniswap V3 sUSD/SNX",
          "chain": "Ethereum",
          "sell_susd": 49077,
          "buy_susd": 46467,
          "attribution_source": "measured",
          "swap_count": 207,
          "programmatic_susd": 0,
          "organic_susd": 46467
        },
        {
          "id": "velo_usdc_susd",
          "dex": "velodrome",
          "label": "Velodrome V2 USDC/sUSD",
          "chain": "Optimism",
          "sell_susd": 41483,
          "buy_susd": 27561,
          "attribution_source": "measured",
          "swap_count": 12528,
          "programmatic_susd": 0,
          "organic_susd": 27561
        },
        {
          "id": "uni_susd_weth",
          "dex": "uniswap",
          "label": "Uniswap V2 sUSD/WETH",
          "chain": "Ethereum",
          "sell_susd": 23073,
          "buy_susd": 22879,
          "attribution_source": "measured",
          "swap_count": 290,
          "programmatic_susd": 0,
          "organic_susd": 22879
        },
        {
          "id": "sushi_susd_weth",
          "dex": "sushiswap",
          "label": "Sushiswap sUSD/WETH",
          "chain": "Ethereum",
          "sell_susd": 143,
          "buy_susd": 138,
          "attribution_source": "measured",
          "swap_count": 29,
          "programmatic_susd": 0,
          "organic_susd": 138
        }
      ],
      "sell_counter_assets": {
        "sUSDe": 0.4747,
        "SNX": 0.2266,
        "USDC": 0.1915,
        "WETH": 0.1072
      },
      "buy_counter_assets": {
        "sUSDe": 0.4697,
        "SNX": 0.2539,
        "USDC": 0.1506,
        "WETH": 0.1258
      },
      "buy_split": {
        "programmatic_susd": 0,
        "organic_susd": 183000,
        "programmatic_share": 0.0
      }
    }
  }
}
