{
  "as_of": "2026-05-24T08:43:31Z",
  "windows": {
    "24h": {
      "total": {
        "sell_susd": 28730,
        "buy_susd": 17455,
        "net_susd": -11275
      },
      "venues": [
        {
          "id": "curve_susde",
          "dex": "curve",
          "label": "Curve sUSD/sUSDe",
          "chain": "Ethereum",
          "sell_susd": 8797,
          "buy_susd": 7947,
          "attribution_source": "measured",
          "swap_count": 60,
          "programmatic_susd": 0,
          "organic_susd": 7947
        },
        {
          "id": "uni_susd_snx",
          "dex": "uniswap",
          "label": "Uniswap V3 sUSD/SNX",
          "chain": "Ethereum",
          "sell_susd": 5473,
          "buy_susd": 0,
          "attribution_source": "measured",
          "swap_count": 17,
          "programmatic_susd": 0,
          "organic_susd": 0
        },
        {
          "id": "velo_usdc_susd",
          "dex": "velodrome",
          "label": "Velodrome V2 USDC/sUSD",
          "chain": "Optimism",
          "sell_susd": 9665,
          "buy_susd": 7964,
          "attribution_source": "measured",
          "swap_count": 1375,
          "programmatic_susd": 0,
          "organic_susd": 7964
        },
        {
          "id": "uni_susd_weth",
          "dex": "uniswap",
          "label": "Uniswap V2 sUSD/WETH",
          "chain": "Ethereum",
          "sell_susd": 2597,
          "buy_susd": 882,
          "attribution_source": "measured",
          "swap_count": 33,
          "programmatic_susd": 0,
          "organic_susd": 882
        },
        {
          "id": "sushi_susd_weth",
          "dex": "sushiswap",
          "label": "Sushiswap sUSD/WETH",
          "chain": "Ethereum",
          "sell_susd": 2198,
          "buy_susd": 662,
          "attribution_source": "measured",
          "swap_count": 25,
          "programmatic_susd": 0,
          "organic_susd": 662
        }
      ],
      "sell_counter_assets": {
        "sUSDe": 0.3062,
        "SNX": 0.1905,
        "USDC": 0.3364,
        "WETH": 0.1669
      },
      "buy_counter_assets": {
        "sUSDe": 0.4553,
        "SNX": 0.0,
        "USDC": 0.4563,
        "WETH": 0.0885
      },
      "buy_split": {
        "programmatic_susd": 0,
        "organic_susd": 17455,
        "programmatic_share": 0.0
      }
    },
    "7d": {
      "total": {
        "sell_susd": 186659,
        "buy_susd": 196779,
        "net_susd": 10120
      },
      "venues": [
        {
          "id": "curve_susde",
          "dex": "curve",
          "label": "Curve sUSD/sUSDe",
          "chain": "Ethereum",
          "sell_susd": 78810,
          "buy_susd": 79286,
          "attribution_source": "measured",
          "swap_count": 293,
          "programmatic_susd": 0,
          "organic_susd": 79286
        },
        {
          "id": "uni_susd_snx",
          "dex": "uniswap",
          "label": "Uniswap V3 sUSD/SNX",
          "chain": "Ethereum",
          "sell_susd": 32399,
          "buy_susd": 41245,
          "attribution_source": "measured",
          "swap_count": 131,
          "programmatic_susd": 0,
          "organic_susd": 41245
        },
        {
          "id": "velo_usdc_susd",
          "dex": "velodrome",
          "label": "Velodrome V2 USDC/sUSD",
          "chain": "Optimism",
          "sell_susd": 38539,
          "buy_susd": 37521,
          "attribution_source": "measured",
          "swap_count": 6027,
          "programmatic_susd": 0,
          "organic_susd": 37521
        },
        {
          "id": "uni_susd_weth",
          "dex": "uniswap",
          "label": "Uniswap V2 sUSD/WETH",
          "chain": "Ethereum",
          "sell_susd": 21615,
          "buy_susd": 22572,
          "attribution_source": "measured",
          "swap_count": 208,
          "programmatic_susd": 0,
          "organic_susd": 22572
        },
        {
          "id": "sushi_susd_weth",
          "dex": "sushiswap",
          "label": "Sushiswap sUSD/WETH",
          "chain": "Ethereum",
          "sell_susd": 15296,
          "buy_susd": 16155,
          "attribution_source": "measured",
          "swap_count": 191,
          "programmatic_susd": 0,
          "organic_susd": 16155
        }
      ],
      "sell_counter_assets": {
        "sUSDe": 0.4222,
        "SNX": 0.1736,
        "USDC": 0.2065,
        "WETH": 0.1977
      },
      "buy_counter_assets": {
        "sUSDe": 0.4029,
        "SNX": 0.2096,
        "USDC": 0.1907,
        "WETH": 0.1968
      },
      "buy_split": {
        "programmatic_susd": 0,
        "organic_susd": 196779,
        "programmatic_share": 0.0
      }
    }
  }
}
