{
  "as_of": "2026-05-19T23:58:06Z",
  "windows": {
    "24h": {
      "total": {
        "sell_susd": 8348,
        "buy_susd": 4223,
        "net_susd": -4125
      },
      "venues": [
        {
          "id": "curve_susde",
          "dex": "curve",
          "label": "Curve sUSD/sUSDe",
          "chain": "Ethereum",
          "sell_susd": 3632,
          "buy_susd": 1507,
          "attribution_source": "measured",
          "swap_count": 12,
          "programmatic_susd": 0,
          "organic_susd": 1507
        },
        {
          "id": "uni_susd_snx",
          "dex": "uniswap",
          "label": "Uniswap V3 sUSD/SNX",
          "chain": "Ethereum",
          "sell_susd": 1215,
          "buy_susd": 0,
          "attribution_source": "measured",
          "swap_count": 4,
          "programmatic_susd": 0,
          "organic_susd": 0
        },
        {
          "id": "velo_usdc_susd",
          "dex": "velodrome",
          "label": "Velodrome V2 USDC/sUSD",
          "chain": "Optimism",
          "sell_susd": 808,
          "buy_susd": 787,
          "attribution_source": "measured",
          "swap_count": 373,
          "programmatic_susd": 0,
          "organic_susd": 787
        },
        {
          "id": "uni_susd_weth",
          "dex": "uniswap",
          "label": "Uniswap V2 sUSD/WETH",
          "chain": "Ethereum",
          "sell_susd": 1401,
          "buy_susd": 992,
          "attribution_source": "measured",
          "swap_count": 11,
          "programmatic_susd": 0,
          "organic_susd": 992
        },
        {
          "id": "sushi_susd_weth",
          "dex": "sushiswap",
          "label": "Sushiswap sUSD/WETH",
          "chain": "Ethereum",
          "sell_susd": 1292,
          "buy_susd": 937,
          "attribution_source": "measured",
          "swap_count": 10,
          "programmatic_susd": 0,
          "organic_susd": 937
        }
      ],
      "sell_counter_assets": {
        "sUSDe": 0.4351,
        "SNX": 0.1455,
        "USDC": 0.0968,
        "WETH": 0.3226
      },
      "buy_counter_assets": {
        "sUSDe": 0.3569,
        "SNX": 0.0,
        "USDC": 0.1864,
        "WETH": 0.4568
      },
      "buy_split": {
        "programmatic_susd": 0,
        "organic_susd": 4223,
        "programmatic_share": 0.0
      }
    },
    "7d": {
      "total": {
        "sell_susd": 223297,
        "buy_susd": 251105,
        "net_susd": 27808
      },
      "venues": [
        {
          "id": "curve_susde",
          "dex": "curve",
          "label": "Curve sUSD/sUSDe",
          "chain": "Ethereum",
          "sell_susd": 104962,
          "buy_susd": 102786,
          "attribution_source": "measured",
          "swap_count": 249,
          "programmatic_susd": 0,
          "organic_susd": 102786
        },
        {
          "id": "uni_susd_snx",
          "dex": "uniswap",
          "label": "Uniswap V3 sUSD/SNX",
          "chain": "Ethereum",
          "sell_susd": 32455,
          "buy_susd": 58685,
          "attribution_source": "measured",
          "swap_count": 150,
          "programmatic_susd": 0,
          "organic_susd": 58685
        },
        {
          "id": "velo_usdc_susd",
          "dex": "velodrome",
          "label": "Velodrome V2 USDC/sUSD",
          "chain": "Optimism",
          "sell_susd": 43021,
          "buy_susd": 43510,
          "attribution_source": "measured",
          "swap_count": 4036,
          "programmatic_susd": 0,
          "organic_susd": 43510
        },
        {
          "id": "uni_susd_weth",
          "dex": "uniswap",
          "label": "Uniswap V2 sUSD/WETH",
          "chain": "Ethereum",
          "sell_susd": 21962,
          "buy_susd": 23674,
          "attribution_source": "measured",
          "swap_count": 184,
          "programmatic_susd": 0,
          "organic_susd": 23674
        },
        {
          "id": "sushi_susd_weth",
          "dex": "sushiswap",
          "label": "Sushiswap sUSD/WETH",
          "chain": "Ethereum",
          "sell_susd": 20897,
          "buy_susd": 22450,
          "attribution_source": "measured",
          "swap_count": 177,
          "programmatic_susd": 0,
          "organic_susd": 22450
        }
      ],
      "sell_counter_assets": {
        "sUSDe": 0.4701,
        "SNX": 0.1453,
        "USDC": 0.1927,
        "WETH": 0.1919
      },
      "buy_counter_assets": {
        "sUSDe": 0.4093,
        "SNX": 0.2337,
        "USDC": 0.1733,
        "WETH": 0.1837
      },
      "buy_split": {
        "programmatic_susd": 0,
        "organic_susd": 251105,
        "programmatic_share": 0.0
      }
    }
  }
}
