{
  "as_of": "2026-06-04T16:58:38Z",
  "windows": {
    "24h": {
      "total": {
        "sell_susd": 66999,
        "buy_susd": 61658,
        "net_susd": -5341
      },
      "venues": [
        {
          "id": "curve_susde",
          "dex": "curve",
          "label": "Curve sUSD/sUSDe",
          "chain": "Ethereum",
          "sell_susd": 35896,
          "buy_susd": 32552,
          "attribution_source": "measured",
          "swap_count": 137,
          "programmatic_susd": 0,
          "organic_susd": 32552
        },
        {
          "id": "uni_susd_snx",
          "dex": "uniswap",
          "label": "Uniswap V3 sUSD/SNX",
          "chain": "Ethereum",
          "sell_susd": 11168,
          "buy_susd": 11234,
          "attribution_source": "measured",
          "swap_count": 48,
          "programmatic_susd": 0,
          "organic_susd": 11234
        },
        {
          "id": "velo_usdc_susd",
          "dex": "velodrome",
          "label": "Velodrome V2 USDC/sUSD",
          "chain": "Optimism",
          "sell_susd": 9830,
          "buy_susd": 8043,
          "attribution_source": "measured",
          "swap_count": 2324,
          "programmatic_susd": 0,
          "organic_susd": 8043
        },
        {
          "id": "uni_susd_weth",
          "dex": "uniswap",
          "label": "Uniswap V2 sUSD/WETH",
          "chain": "Ethereum",
          "sell_susd": 10056,
          "buy_susd": 9791,
          "attribution_source": "measured",
          "swap_count": 78,
          "programmatic_susd": 0,
          "organic_susd": 9791
        },
        {
          "id": "sushi_susd_weth",
          "dex": "sushiswap",
          "label": "Sushiswap sUSD/WETH",
          "chain": "Ethereum",
          "sell_susd": 49,
          "buy_susd": 38,
          "attribution_source": "measured",
          "swap_count": 6,
          "programmatic_susd": 0,
          "organic_susd": 38
        }
      ],
      "sell_counter_assets": {
        "sUSDe": 0.5358,
        "SNX": 0.1667,
        "USDC": 0.1467,
        "WETH": 0.1508
      },
      "buy_counter_assets": {
        "sUSDe": 0.5279,
        "SNX": 0.1822,
        "USDC": 0.1304,
        "WETH": 0.1594
      },
      "buy_split": {
        "programmatic_susd": 0,
        "organic_susd": 61658,
        "programmatic_share": 0.0
      }
    },
    "7d": {
      "total": {
        "sell_susd": 213363,
        "buy_susd": 186848,
        "net_susd": -26515
      },
      "venues": [
        {
          "id": "curve_susde",
          "dex": "curve",
          "label": "Curve sUSD/sUSDe",
          "chain": "Ethereum",
          "sell_susd": 103741,
          "buy_susd": 89325,
          "attribution_source": "measured",
          "swap_count": 416,
          "programmatic_susd": 0,
          "organic_susd": 89325
        },
        {
          "id": "uni_susd_snx",
          "dex": "uniswap",
          "label": "Uniswap V3 sUSD/SNX",
          "chain": "Ethereum",
          "sell_susd": 66925,
          "buy_susd": 62484,
          "attribution_source": "measured",
          "swap_count": 216,
          "programmatic_susd": 0,
          "organic_susd": 62484
        },
        {
          "id": "velo_usdc_susd",
          "dex": "velodrome",
          "label": "Velodrome V2 USDC/sUSD",
          "chain": "Optimism",
          "sell_susd": 21347,
          "buy_susd": 14057,
          "attribution_source": "measured",
          "swap_count": 7327,
          "programmatic_susd": 0,
          "organic_susd": 14057
        },
        {
          "id": "uni_susd_weth",
          "dex": "uniswap",
          "label": "Uniswap V2 sUSD/WETH",
          "chain": "Ethereum",
          "sell_susd": 21219,
          "buy_susd": 20870,
          "attribution_source": "measured",
          "swap_count": 223,
          "programmatic_susd": 0,
          "organic_susd": 20870
        },
        {
          "id": "sushi_susd_weth",
          "dex": "sushiswap",
          "label": "Sushiswap sUSD/WETH",
          "chain": "Ethereum",
          "sell_susd": 131,
          "buy_susd": 112,
          "attribution_source": "measured",
          "swap_count": 24,
          "programmatic_susd": 0,
          "organic_susd": 112
        }
      ],
      "sell_counter_assets": {
        "sUSDe": 0.4862,
        "SNX": 0.3137,
        "USDC": 0.1001,
        "WETH": 0.1001
      },
      "buy_counter_assets": {
        "sUSDe": 0.4781,
        "SNX": 0.3344,
        "USDC": 0.0752,
        "WETH": 0.1123
      },
      "buy_split": {
        "programmatic_susd": 0,
        "organic_susd": 186848,
        "programmatic_share": 0.0
      }
    }
  }
}
