{
  "as_of": "2026-05-19T19:57:34Z",
  "windows": {
    "24h": {
      "total": {
        "sell_susd": 9344,
        "buy_susd": 5256,
        "net_susd": -4088
      },
      "venues": [
        {
          "id": "curve_susde",
          "dex": "curve",
          "label": "Curve sUSD/sUSDe",
          "chain": "Ethereum",
          "sell_susd": 3629,
          "buy_susd": 2358,
          "attribution_source": "measured",
          "swap_count": 16,
          "programmatic_susd": 0,
          "organic_susd": 2358
        },
        {
          "id": "uni_susd_snx",
          "dex": "uniswap",
          "label": "Uniswap V3 sUSD/SNX",
          "chain": "Ethereum",
          "sell_susd": 2236,
          "buy_susd": 0,
          "attribution_source": "measured",
          "swap_count": 9,
          "programmatic_susd": 0,
          "organic_susd": 0
        },
        {
          "id": "velo_usdc_susd",
          "dex": "velodrome",
          "label": "Velodrome V2 USDC/sUSD",
          "chain": "Optimism",
          "sell_susd": 766,
          "buy_susd": 804,
          "attribution_source": "measured",
          "swap_count": 441,
          "programmatic_susd": 0,
          "organic_susd": 804
        },
        {
          "id": "uni_susd_weth",
          "dex": "uniswap",
          "label": "Uniswap V2 sUSD/WETH",
          "chain": "Ethereum",
          "sell_susd": 1400,
          "buy_susd": 1118,
          "attribution_source": "measured",
          "swap_count": 10,
          "programmatic_susd": 0,
          "organic_susd": 1118
        },
        {
          "id": "sushi_susd_weth",
          "dex": "sushiswap",
          "label": "Sushiswap sUSD/WETH",
          "chain": "Ethereum",
          "sell_susd": 1313,
          "buy_susd": 976,
          "attribution_source": "measured",
          "swap_count": 15,
          "programmatic_susd": 0,
          "organic_susd": 976
        }
      ],
      "sell_counter_assets": {
        "sUSDe": 0.3884,
        "SNX": 0.2393,
        "USDC": 0.082,
        "WETH": 0.2903
      },
      "buy_counter_assets": {
        "sUSDe": 0.4486,
        "SNX": 0.0,
        "USDC": 0.153,
        "WETH": 0.3984
      },
      "buy_split": {
        "programmatic_susd": 0,
        "organic_susd": 5256,
        "programmatic_share": 0.0
      }
    },
    "7d": {
      "total": {
        "sell_susd": 223368,
        "buy_susd": 253995,
        "net_susd": 30627
      },
      "venues": [
        {
          "id": "curve_susde",
          "dex": "curve",
          "label": "Curve sUSD/sUSDe",
          "chain": "Ethereum",
          "sell_susd": 104942,
          "buy_susd": 104185,
          "attribution_source": "measured",
          "swap_count": 251,
          "programmatic_susd": 0,
          "organic_susd": 104185
        },
        {
          "id": "uni_susd_snx",
          "dex": "uniswap",
          "label": "Uniswap V3 sUSD/SNX",
          "chain": "Ethereum",
          "sell_susd": 32428,
          "buy_susd": 58637,
          "attribution_source": "measured",
          "swap_count": 150,
          "programmatic_susd": 0,
          "organic_susd": 58637
        },
        {
          "id": "velo_usdc_susd",
          "dex": "velodrome",
          "label": "Velodrome V2 USDC/sUSD",
          "chain": "Optimism",
          "sell_susd": 43175,
          "buy_susd": 44291,
          "attribution_source": "measured",
          "swap_count": 4053,
          "programmatic_susd": 0,
          "organic_susd": 44291
        },
        {
          "id": "uni_susd_weth",
          "dex": "uniswap",
          "label": "Uniswap V2 sUSD/WETH",
          "chain": "Ethereum",
          "sell_susd": 21943,
          "buy_susd": 24081,
          "attribution_source": "measured",
          "swap_count": 184,
          "programmatic_susd": 0,
          "organic_susd": 24081
        },
        {
          "id": "sushi_susd_weth",
          "dex": "sushiswap",
          "label": "Sushiswap sUSD/WETH",
          "chain": "Ethereum",
          "sell_susd": 20880,
          "buy_susd": 22801,
          "attribution_source": "measured",
          "swap_count": 179,
          "programmatic_susd": 0,
          "organic_susd": 22801
        }
      ],
      "sell_counter_assets": {
        "sUSDe": 0.4698,
        "SNX": 0.1452,
        "USDC": 0.1933,
        "WETH": 0.1917
      },
      "buy_counter_assets": {
        "sUSDe": 0.4102,
        "SNX": 0.2309,
        "USDC": 0.1744,
        "WETH": 0.1846
      },
      "buy_split": {
        "programmatic_susd": 0,
        "organic_susd": 253995,
        "programmatic_share": 0.0
      }
    }
  }
}
