{
  "as_of": "2026-06-10T16:29:52Z",
  "windows": {
    "24h": {
      "total": {
        "sell_susd": 9543,
        "buy_susd": 5905,
        "net_susd": -3638
      },
      "venues": [
        {
          "id": "curve_susde",
          "dex": "curve",
          "label": "Curve sUSD/sUSDe",
          "chain": "Ethereum",
          "sell_susd": 3873,
          "buy_susd": 3854,
          "attribution_source": "measured",
          "swap_count": 52,
          "programmatic_susd": 0,
          "organic_susd": 3854
        },
        {
          "id": "uni_susd_snx",
          "dex": "uniswap",
          "label": "Uniswap V3 sUSD/SNX",
          "chain": "Ethereum",
          "sell_susd": 3736,
          "buy_susd": 575,
          "attribution_source": "measured",
          "swap_count": 15,
          "programmatic_susd": 0,
          "organic_susd": 575
        },
        {
          "id": "velo_usdc_susd",
          "dex": "velodrome",
          "label": "Velodrome V2 USDC/sUSD",
          "chain": "Optimism",
          "sell_susd": 348,
          "buy_susd": 259,
          "attribution_source": "measured",
          "swap_count": 712,
          "programmatic_susd": 0,
          "organic_susd": 259
        },
        {
          "id": "uni_susd_weth",
          "dex": "uniswap",
          "label": "Uniswap V2 sUSD/WETH",
          "chain": "Ethereum",
          "sell_susd": 1586,
          "buy_susd": 1209,
          "attribution_source": "measured",
          "swap_count": 30,
          "programmatic_susd": 0,
          "organic_susd": 1209
        },
        {
          "id": "sushi_susd_weth",
          "dex": "sushiswap",
          "label": "Sushiswap sUSD/WETH",
          "chain": "Ethereum",
          "sell_susd": 0,
          "buy_susd": 8,
          "attribution_source": "measured",
          "swap_count": 3,
          "programmatic_susd": 0,
          "organic_susd": 8
        }
      ],
      "sell_counter_assets": {
        "sUSDe": 0.4058,
        "SNX": 0.3915,
        "USDC": 0.0365,
        "WETH": 0.1662
      },
      "buy_counter_assets": {
        "sUSDe": 0.6527,
        "SNX": 0.0974,
        "USDC": 0.0439,
        "WETH": 0.2061
      },
      "buy_split": {
        "programmatic_susd": 0,
        "organic_susd": 5905,
        "programmatic_share": 0.0
      }
    },
    "7d": {
      "total": {
        "sell_susd": 193806,
        "buy_susd": 157928,
        "net_susd": -35878
      },
      "venues": [
        {
          "id": "curve_susde",
          "dex": "curve",
          "label": "Curve sUSD/sUSDe",
          "chain": "Ethereum",
          "sell_susd": 91113,
          "buy_susd": 76547,
          "attribution_source": "measured",
          "swap_count": 560,
          "programmatic_susd": 0,
          "organic_susd": 76547
        },
        {
          "id": "uni_susd_snx",
          "dex": "uniswap",
          "label": "Uniswap V3 sUSD/SNX",
          "chain": "Ethereum",
          "sell_susd": 41289,
          "buy_susd": 31154,
          "attribution_source": "measured",
          "swap_count": 181,
          "programmatic_susd": 0,
          "organic_susd": 31154
        },
        {
          "id": "velo_usdc_susd",
          "dex": "velodrome",
          "label": "Velodrome V2 USDC/sUSD",
          "chain": "Optimism",
          "sell_susd": 39663,
          "buy_susd": 30143,
          "attribution_source": "measured",
          "swap_count": 11444,
          "programmatic_susd": 0,
          "organic_susd": 30143
        },
        {
          "id": "uni_susd_weth",
          "dex": "uniswap",
          "label": "Uniswap V2 sUSD/WETH",
          "chain": "Ethereum",
          "sell_susd": 21597,
          "buy_susd": 19969,
          "attribution_source": "measured",
          "swap_count": 278,
          "programmatic_susd": 0,
          "organic_susd": 19969
        },
        {
          "id": "sushi_susd_weth",
          "dex": "sushiswap",
          "label": "Sushiswap sUSD/WETH",
          "chain": "Ethereum",
          "sell_susd": 144,
          "buy_susd": 115,
          "attribution_source": "measured",
          "swap_count": 28,
          "programmatic_susd": 0,
          "organic_susd": 115
        }
      ],
      "sell_counter_assets": {
        "sUSDe": 0.4701,
        "SNX": 0.213,
        "USDC": 0.2047,
        "WETH": 0.1122
      },
      "buy_counter_assets": {
        "sUSDe": 0.4847,
        "SNX": 0.1973,
        "USDC": 0.1909,
        "WETH": 0.1272
      },
      "buy_split": {
        "programmatic_susd": 0,
        "organic_susd": 157928,
        "programmatic_share": 0.0
      }
    }
  }
}
