{
  "as_of": "2026-06-05T08:43:52Z",
  "windows": {
    "24h": {
      "total": {
        "sell_susd": 56692,
        "buy_susd": 39184,
        "net_susd": -17508
      },
      "venues": [
        {
          "id": "curve_susde",
          "dex": "curve",
          "label": "Curve sUSD/sUSDe",
          "chain": "Ethereum",
          "sell_susd": 26629,
          "buy_susd": 13312,
          "attribution_source": "illustrative",
          "swap_count": null,
          "programmatic_susd": null,
          "organic_susd": null
        },
        {
          "id": "uni_susd_snx",
          "dex": "uniswap",
          "label": "Uniswap V3 sUSD/SNX",
          "chain": "Ethereum",
          "sell_susd": 10738,
          "buy_susd": 7671,
          "attribution_source": "illustrative",
          "swap_count": null,
          "programmatic_susd": null,
          "organic_susd": null
        },
        {
          "id": "velo_usdc_susd",
          "dex": "velodrome",
          "label": "Velodrome V2 USDC/sUSD",
          "chain": "Optimism",
          "sell_susd": 12637,
          "buy_susd": 10790,
          "attribution_source": "measured",
          "swap_count": 2348,
          "programmatic_susd": 0,
          "organic_susd": 10790
        },
        {
          "id": "uni_susd_weth",
          "dex": "uniswap",
          "label": "Uniswap V2 sUSD/WETH",
          "chain": "Ethereum",
          "sell_susd": 6663,
          "buy_susd": 7349,
          "attribution_source": "measured",
          "swap_count": 60,
          "programmatic_susd": 0,
          "organic_susd": 7349
        },
        {
          "id": "sushi_susd_weth",
          "dex": "sushiswap",
          "label": "Sushiswap sUSD/WETH",
          "chain": "Ethereum",
          "sell_susd": 25,
          "buy_susd": 62,
          "attribution_source": "measured",
          "swap_count": 7,
          "programmatic_susd": 0,
          "organic_susd": 62
        }
      ],
      "sell_counter_assets": {
        "USDC": 0.2756,
        "WETH": 0.1641,
        "sUSDe": 0.4614,
        "SNX": 0.0989
      },
      "buy_counter_assets": {
        "USDC": 0.3182,
        "WETH": 0.2213,
        "sUSDe": 0.3534,
        "SNX": 0.1071
      },
      "buy_split": {
        "programmatic_susd": 5036,
        "organic_susd": 34148,
        "programmatic_share": 0.1285
      }
    },
    "7d": {
      "total": {
        "sell_susd": 212466,
        "buy_susd": 189731,
        "net_susd": -22735
      },
      "venues": [
        {
          "id": "curve_susde",
          "dex": "curve",
          "label": "Curve sUSD/sUSDe",
          "chain": "Ethereum",
          "sell_susd": 105570,
          "buy_susd": 85780,
          "attribution_source": "measured",
          "swap_count": 445,
          "programmatic_susd": 0,
          "organic_susd": 85780
        },
        {
          "id": "uni_susd_snx",
          "dex": "uniswap",
          "label": "Uniswap V3 sUSD/SNX",
          "chain": "Ethereum",
          "sell_susd": 57122,
          "buy_susd": 66712,
          "attribution_source": "measured",
          "swap_count": 217,
          "programmatic_susd": 0,
          "organic_susd": 66712
        },
        {
          "id": "velo_usdc_susd",
          "dex": "velodrome",
          "label": "Velodrome V2 USDC/sUSD",
          "chain": "Optimism",
          "sell_susd": 28176,
          "buy_susd": 15653,
          "attribution_source": "measured",
          "swap_count": 8331,
          "programmatic_susd": 0,
          "organic_susd": 15653
        },
        {
          "id": "uni_susd_weth",
          "dex": "uniswap",
          "label": "Uniswap V2 sUSD/WETH",
          "chain": "Ethereum",
          "sell_susd": 21482,
          "buy_susd": 21463,
          "attribution_source": "measured",
          "swap_count": 239,
          "programmatic_susd": 0,
          "organic_susd": 21463
        },
        {
          "id": "sushi_susd_weth",
          "dex": "sushiswap",
          "label": "Sushiswap sUSD/WETH",
          "chain": "Ethereum",
          "sell_susd": 116,
          "buy_susd": 123,
          "attribution_source": "measured",
          "swap_count": 25,
          "programmatic_susd": 0,
          "organic_susd": 123
        }
      ],
      "sell_counter_assets": {
        "sUSDe": 0.4969,
        "SNX": 0.2689,
        "USDC": 0.1326,
        "WETH": 0.1017
      },
      "buy_counter_assets": {
        "sUSDe": 0.4521,
        "SNX": 0.3516,
        "USDC": 0.0825,
        "WETH": 0.1138
      },
      "buy_split": {
        "programmatic_susd": 0,
        "organic_susd": 189731,
        "programmatic_share": 0.0
      }
    }
  }
}
