{
  "as_of": "2026-05-04T09:08:09Z",
  "windows": {
    "24h": {
      "total": {
        "sell_susd": 14938,
        "buy_susd": 8133,
        "net_susd": -6805
      },
      "venues": [
        {
          "id": "curve_susde",
          "dex": "curve",
          "label": "Curve sUSD/sUSDe",
          "chain": "Ethereum",
          "sell_susd": 5293,
          "buy_susd": 2646
        },
        {
          "id": "uni_susd_snx",
          "dex": "uniswap",
          "label": "Uniswap V3 sUSD/SNX",
          "chain": "Ethereum",
          "sell_susd": 3441,
          "buy_susd": 2459
        },
        {
          "id": "velo_usdc_susd",
          "dex": "velodrome",
          "label": "Velodrome V2 USDC/sUSD",
          "chain": "Optimism",
          "sell_susd": 3849,
          "buy_susd": 2124
        },
        {
          "id": "uni_susd_weth",
          "dex": "uniswap",
          "label": "Uniswap V2 sUSD/WETH",
          "chain": "Ethereum",
          "sell_susd": 1091,
          "buy_susd": 588
        },
        {
          "id": "sushi_susd_weth",
          "dex": "sushiswap",
          "label": "Sushiswap sUSD/WETH",
          "chain": "Ethereum",
          "sell_susd": 1264,
          "buy_susd": 316
        }
      ],
      "sell_counter_assets": {
        "sUSDe": 0.7,
        "SNX": 0.15,
        "USDC": 0.08,
        "WETH": 0.07
      },
      "buy_counter_assets": {
        "sUSDe": 0.66,
        "SNX": 0.2,
        "USDC": 0.08,
        "WETH": 0.06
      },
      "buy_split": {
        "programmatic_susd": 1952,
        "organic_susd": 6181,
        "programmatic_share": 0.24
      }
    },
    "7d": {
      "total": {
        "sell_susd": 104571,
        "buy_susd": 56926,
        "net_susd": -47645
      },
      "venues": [
        {
          "id": "curve_susde",
          "dex": "curve",
          "label": "Curve sUSD/sUSDe",
          "chain": "Ethereum",
          "sell_susd": 37051,
          "buy_susd": 18522
        },
        {
          "id": "uni_susd_snx",
          "dex": "uniswap",
          "label": "Uniswap V3 sUSD/SNX",
          "chain": "Ethereum",
          "sell_susd": 24090,
          "buy_susd": 17210
        },
        {
          "id": "velo_usdc_susd",
          "dex": "velodrome",
          "label": "Velodrome V2 USDC/sUSD",
          "chain": "Optimism",
          "sell_susd": 26943,
          "buy_susd": 14868
        },
        {
          "id": "uni_susd_weth",
          "dex": "uniswap",
          "label": "Uniswap V2 sUSD/WETH",
          "chain": "Ethereum",
          "sell_susd": 7639,
          "buy_susd": 4114
        },
        {
          "id": "sushi_susd_weth",
          "dex": "sushiswap",
          "label": "Sushiswap sUSD/WETH",
          "chain": "Ethereum",
          "sell_susd": 8848,
          "buy_susd": 2212
        }
      ],
      "sell_counter_assets": {
        "sUSDe": 0.69,
        "SNX": 0.16,
        "USDC": 0.08,
        "WETH": 0.07
      },
      "buy_counter_assets": {
        "sUSDe": 0.65,
        "SNX": 0.21,
        "USDC": 0.08,
        "WETH": 0.06
      },
      "buy_split": {
        "programmatic_susd": 13605,
        "organic_susd": 43321,
        "programmatic_share": 0.239
      }
    }
  }
}
