{
  "as_of": "2026-05-28T14:01:59Z",
  "windows": {
    "24h": {
      "total": {
        "sell_susd": 81632,
        "buy_susd": 110378,
        "net_susd": 28746
      },
      "venues": [
        {
          "id": "curve_susde",
          "dex": "curve",
          "label": "Curve sUSD/sUSDe",
          "chain": "Ethereum",
          "sell_susd": 57722,
          "buy_susd": 63392,
          "attribution_source": "measured",
          "swap_count": 96,
          "programmatic_susd": 0,
          "organic_susd": 63392
        },
        {
          "id": "uni_susd_snx",
          "dex": "uniswap",
          "label": "Uniswap V3 sUSD/SNX",
          "chain": "Ethereum",
          "sell_susd": 7078,
          "buy_susd": 34301,
          "attribution_source": "measured",
          "swap_count": 55,
          "programmatic_susd": 0,
          "organic_susd": 34301
        },
        {
          "id": "velo_usdc_susd",
          "dex": "velodrome",
          "label": "Velodrome V2 USDC/sUSD",
          "chain": "Optimism",
          "sell_susd": 3578,
          "buy_susd": 5419,
          "attribution_source": "measured",
          "swap_count": 724,
          "programmatic_susd": 0,
          "organic_susd": 5419
        },
        {
          "id": "uni_susd_weth",
          "dex": "uniswap",
          "label": "Uniswap V2 sUSD/WETH",
          "chain": "Ethereum",
          "sell_susd": 13114,
          "buy_susd": 7061,
          "attribution_source": "illustrative",
          "swap_count": null,
          "programmatic_susd": null,
          "organic_susd": null
        },
        {
          "id": "sushi_susd_weth",
          "dex": "sushiswap",
          "label": "Sushiswap sUSD/WETH",
          "chain": "Ethereum",
          "sell_susd": 140,
          "buy_susd": 205,
          "attribution_source": "measured",
          "swap_count": 11,
          "programmatic_susd": 0,
          "organic_susd": 205
        }
      ],
      "sell_counter_assets": {
        "sUSDe": 0.8196,
        "SNX": 0.1108,
        "USDC": 0.0567,
        "WETH": 0.013
      },
      "buy_counter_assets": {
        "sUSDe": 0.6165,
        "SNX": 0.3236,
        "USDC": 0.0542,
        "WETH": 0.0057
      },
      "buy_split": {
        "programmatic_susd": 1695,
        "organic_susd": 108683,
        "programmatic_share": 0.0154
      }
    },
    "7d": {
      "total": {
        "sell_susd": 319523,
        "buy_susd": 349094,
        "net_susd": 29571
      },
      "venues": [
        {
          "id": "curve_susde",
          "dex": "curve",
          "label": "Curve sUSD/sUSDe",
          "chain": "Ethereum",
          "sell_susd": 181355,
          "buy_susd": 185287,
          "attribution_source": "measured",
          "swap_count": 432,
          "programmatic_susd": 0,
          "organic_susd": 185287
        },
        {
          "id": "uni_susd_snx",
          "dex": "uniswap",
          "label": "Uniswap V3 sUSD/SNX",
          "chain": "Ethereum",
          "sell_susd": 60549,
          "buy_susd": 80932,
          "attribution_source": "measured",
          "swap_count": 225,
          "programmatic_susd": 0,
          "organic_susd": 80932
        },
        {
          "id": "velo_usdc_susd",
          "dex": "velodrome",
          "label": "Velodrome V2 USDC/sUSD",
          "chain": "Optimism",
          "sell_susd": 41105,
          "buy_susd": 43147,
          "attribution_source": "measured",
          "swap_count": 6235,
          "programmatic_susd": 0,
          "organic_susd": 43147
        },
        {
          "id": "uni_susd_weth",
          "dex": "uniswap",
          "label": "Uniswap V2 sUSD/WETH",
          "chain": "Ethereum",
          "sell_susd": 31477,
          "buy_susd": 34424,
          "attribution_source": "measured",
          "swap_count": 285,
          "programmatic_susd": 0,
          "organic_susd": 34424
        },
        {
          "id": "sushi_susd_weth",
          "dex": "sushiswap",
          "label": "Sushiswap sUSD/WETH",
          "chain": "Ethereum",
          "sell_susd": 5037,
          "buy_susd": 5304,
          "attribution_source": "measured",
          "swap_count": 123,
          "programmatic_susd": 0,
          "organic_susd": 5304
        }
      ],
      "sell_counter_assets": {
        "sUSDe": 0.5676,
        "SNX": 0.1895,
        "USDC": 0.1286,
        "WETH": 0.1143
      },
      "buy_counter_assets": {
        "sUSDe": 0.5308,
        "SNX": 0.2318,
        "USDC": 0.1236,
        "WETH": 0.1138
      },
      "buy_split": {
        "programmatic_susd": 0,
        "organic_susd": 349094,
        "programmatic_share": 0.0
      }
    }
  }
}
